LICENSE
firthlogist/.ipynb_checkpoints/test_notebook-checkpoint.ipynb
firthlogist/.pytest_cache/.gitignore
firthlogist/.pytest_cache/CACHEDIR.TAG
firthlogist/.pytest_cache/README.md
firthlogist/.pytest_cache/v/cache/lastfailed
firthlogist/.pytest_cache/v/cache/nodeids
firthlogist/.pytest_cache/v/cache/stepwise
firthlogist/__init__.py
firthlogist/datasets/__init__.py
firthlogist/datasets/endometrial.csv
firthlogist/datasets/sex2.csv
firthlogist/datasets/x21data.npz
firthlogist/firthlogist.py
firthlogist/letter_img.csv
firthlogist/loglike.cpython-310-x86_64-linux-gnu.so
firthlogist/loglike.py
firthlogist/profile.json
firthlogist/test_notebook.ipynb
firthlogist/testaroo.py
firthlogist/tests/.pytest_cache/.gitignore
firthlogist/tests/.pytest_cache/CACHEDIR.TAG
firthlogist/tests/.pytest_cache/README.md
firthlogist/tests/.pytest_cache/v/cache/lastfailed
firthlogist/tests/.pytest_cache/v/cache/nodeids
firthlogist/tests/.pytest_cache/v/cache/stepwise
firthlogist/tests/__init__.py
firthlogist/tests/test_firthlogist.py
firthlogist-0.5.0.dist-info/LICENSE
firthlogist-0.5.0.dist-info/WHEEL
firthlogist-0.5.0.dist-info/METADATA
firthlogist-0.5.0.dist-info/RECORD
