Metadata-Version: 2.1
Name: firthlogist
Version: 0.5.0
Summary: Python implementation of Logistic Regression with Firth's bias reduction
Home-page: https://github.com/jzluo/firthlogist
License: MIT
Author: Jon Luo
Author-email: jzluo@alumni.cmu.edu
Requires-Python: >=3.8,<3.11
Classifier: Intended Audience :: Science/Research
Classifier: License :: OSI Approved :: MIT License
Classifier: Programming Language :: Python :: 3
Classifier: Programming Language :: Python :: 3.10
Classifier: Programming Language :: Python :: 3.8
Classifier: Programming Language :: Python :: 3.9
Classifier: Topic :: Scientific/Engineering
Requires-Dist: numpy (>=1.22.4,<2.0.0)
Requires-Dist: scikit-learn (>=1.1.1,<2.0.0)
Requires-Dist: tabulate (>=0.8.10,<0.9.0)
Project-URL: Repository, https://github.com/jzluo/firthlogist
